dennis/__init__.py
dennis/cmdline.py
dennis/linter.py
dennis/templatelinter.py
dennis/tools.py
dennis/translator.py
tests/__init__.py
tests/test_cmdline.py
tests/test_linter.py
tests/test_tools.py
tests/test_translator.py
dennis-1.1.0.dist-info/LICENSE
dennis-1.1.0.dist-info/METADATA
dennis-1.1.0.dist-info/WHEEL
dennis-1.1.0.dist-info/entry_points.txt
dennis-1.1.0.dist-info/top_level.txt
dennis-1.1.0.dist-info/zip-safe
dennis-1.1.0.dist-info/RECORD
