Metadata-Version: 2.1
Name: dennis
Version: 1.1.0
Summary: Utilities for working with gettext PO and POT files to ease development and improve localization quality
Home-page: https://github.com/mozilla/dennis
Author: Will Kahn-Greene
Maintainer: Mozilla
License: Simplified BSD License
Keywords: l10n localization gettext PO POT lint translate development
Classifier: Development Status :: 5 - Production/Stable
Classifier: Environment :: Console
Classifier: License :: OSI Approved :: BSD License
Classifier: Operating System :: OS Independent
Classifier: Programming Language :: Python
Classifier: Programming Language :: Python :: 3
Classifier: Programming Language :: Python :: 3.7
Classifier: Programming Language :: Python :: 3.8
Classifier: Programming Language :: Python :: 3.9
Classifier: Programming Language :: Python :: 3.10
Classifier: Programming Language :: Python :: 3 :: Only
Classifier: Topic :: Software Development :: Localization
Requires-Python: >=3.7
License-File: LICENSE
Requires-Dist: polib (>=1.0.8)
Requires-Dist: click (>=6)
